{
    "uid": "cf99beb9-a183-4395-a353-59149f9d76f1",
    "name": "3_Xgboost_RandomFeature",
    "preprocessing": [
        {
            "remove_columns": [
                "E_G_total_assets_on_assets_ratio",
                "E_G_total_revenues_on_rev_ratio",
                "E_G_total_capital_on_tot_cap_ratio"
            ],
            "ml_task": "binary_classification",
            "add_random_feature": true,
            "params": {
                "columns_preprocessing": {
                    "E_G_total_assets_on_assets_ratio": [
                        "remove_column"
                    ],
                    "E_G_total_revenues_on_rev_ratio": [
                        "remove_column"
                    ],
                    "E_G_total_capital_on_tot_cap_ratio": [
                        "remove_column"
                    ]
                },
                "target_preprocessing": [
                    "na_exclude"
                ],
                "ml_task": "binary_classification",
                "add_random_feature": true
            }
        },
        {
            "remove_columns": [
                "E_G_total_assets_on_assets_ratio",
                "E_G_total_revenues_on_rev_ratio",
                "E_G_total_capital_on_tot_cap_ratio"
            ],
            "ml_task": "binary_classification",
            "add_random_feature": true,
            "params": {
                "columns_preprocessing": {
                    "E_G_total_assets_on_assets_ratio": [
                        "remove_column"
                    ],
                    "E_G_total_revenues_on_rev_ratio": [
                        "remove_column"
                    ],
                    "E_G_total_capital_on_tot_cap_ratio": [
                        "remove_column"
                    ]
                },
                "target_preprocessing": [
                    "na_exclude"
                ],
                "ml_task": "binary_classification",
                "add_random_feature": true
            }
        },
        {
            "remove_columns": [
                "E_G_total_assets_on_assets_ratio",
                "E_G_total_revenues_on_rev_ratio",
                "E_G_total_capital_on_tot_cap_ratio"
            ],
            "ml_task": "binary_classification",
            "add_random_feature": true,
            "params": {
                "columns_preprocessing": {
                    "E_G_total_assets_on_assets_ratio": [
                        "remove_column"
                    ],
                    "E_G_total_revenues_on_rev_ratio": [
                        "remove_column"
                    ],
                    "E_G_total_capital_on_tot_cap_ratio": [
                        "remove_column"
                    ]
                },
                "target_preprocessing": [
                    "na_exclude"
                ],
                "ml_task": "binary_classification",
                "add_random_feature": true
            }
        },
        {
            "remove_columns": [
                "E_G_total_assets_on_assets_ratio",
                "E_G_total_revenues_on_rev_ratio",
                "E_G_total_capital_on_tot_cap_ratio"
            ],
            "ml_task": "binary_classification",
            "add_random_feature": true,
            "params": {
                "columns_preprocessing": {
                    "E_G_total_assets_on_assets_ratio": [
                        "remove_column"
                    ],
                    "E_G_total_revenues_on_rev_ratio": [
                        "remove_column"
                    ],
                    "E_G_total_capital_on_tot_cap_ratio": [
                        "remove_column"
                    ]
                },
                "target_preprocessing": [
                    "na_exclude"
                ],
                "ml_task": "binary_classification",
                "add_random_feature": true
            }
        },
        {
            "remove_columns": [
                "E_G_total_assets_on_assets_ratio",
                "E_G_total_revenues_on_rev_ratio",
                "E_G_total_capital_on_tot_cap_ratio"
            ],
            "ml_task": "binary_classification",
            "add_random_feature": true,
            "params": {
                "columns_preprocessing": {
                    "E_G_total_assets_on_assets_ratio": [
                        "remove_column"
                    ],
                    "E_G_total_revenues_on_rev_ratio": [
                        "remove_column"
                    ],
                    "E_G_total_capital_on_tot_cap_ratio": [
                        "remove_column"
                    ]
                },
                "target_preprocessing": [
                    "na_exclude"
                ],
                "ml_task": "binary_classification",
                "add_random_feature": true
            }
        }
    ],
    "learners": [
        {
            "library_version": "2.1.1",
            "algorithm_name": "Extreme Gradient Boosting",
            "algorithm_short_name": "Xgboost",
            "uid": "b7cbe720-86a8-4231-888a-e47445d7749e",
            "params": {
                "model_type": "Xgboost",
                "ml_task": "binary_classification",
                "n_jobs": -1,
                "seed": 1236,
                "objective": "binary:logistic",
                "eta": 0.1,
                "max_depth": 8,
                "min_child_weight": 1,
                "subsample": 1.0,
                "colsample_bytree": 1.0,
                "eval_metric": "auc",
                "explain_level": 1
            },
            "name": "learner_fold_0"
        },
        {
            "library_version": "2.1.1",
            "algorithm_name": "Extreme Gradient Boosting",
            "algorithm_short_name": "Xgboost",
            "uid": "7f452218-0143-4333-a0cc-56c18ac4d18f",
            "params": {
                "model_type": "Xgboost",
                "ml_task": "binary_classification",
                "n_jobs": -1,
                "seed": 1236,
                "objective": "binary:logistic",
                "eta": 0.1,
                "max_depth": 8,
                "min_child_weight": 1,
                "subsample": 1.0,
                "colsample_bytree": 1.0,
                "eval_metric": "auc",
                "explain_level": 1
            },
            "name": "learner_fold_1"
        },
        {
            "library_version": "2.1.1",
            "algorithm_name": "Extreme Gradient Boosting",
            "algorithm_short_name": "Xgboost",
            "uid": "28b5cdb4-809a-43b3-a203-22d990dbf422",
            "params": {
                "model_type": "Xgboost",
                "ml_task": "binary_classification",
                "n_jobs": -1,
                "seed": 1236,
                "objective": "binary:logistic",
                "eta": 0.1,
                "max_depth": 8,
                "min_child_weight": 1,
                "subsample": 1.0,
                "colsample_bytree": 1.0,
                "eval_metric": "auc",
                "explain_level": 1
            },
            "name": "learner_fold_2"
        },
        {
            "library_version": "2.1.1",
            "algorithm_name": "Extreme Gradient Boosting",
            "algorithm_short_name": "Xgboost",
            "uid": "f35d22ae-f51c-4f01-9a85-094d7c02597e",
            "params": {
                "model_type": "Xgboost",
                "ml_task": "binary_classification",
                "n_jobs": -1,
                "seed": 1236,
                "objective": "binary:logistic",
                "eta": 0.1,
                "max_depth": 8,
                "min_child_weight": 1,
                "subsample": 1.0,
                "colsample_bytree": 1.0,
                "eval_metric": "auc",
                "explain_level": 1
            },
            "name": "learner_fold_3"
        },
        {
            "library_version": "2.1.1",
            "algorithm_name": "Extreme Gradient Boosting",
            "algorithm_short_name": "Xgboost",
            "uid": "b205665b-a5cc-4c1b-9fcf-621f17335882",
            "params": {
                "model_type": "Xgboost",
                "ml_task": "binary_classification",
                "n_jobs": -1,
                "seed": 1236,
                "objective": "binary:logistic",
                "eta": 0.1,
                "max_depth": 8,
                "min_child_weight": 1,
                "subsample": 1.0,
                "colsample_bytree": 1.0,
                "eval_metric": "auc",
                "explain_level": 1
            },
            "name": "learner_fold_4"
        }
    ],
    "params": {
        "additional": {
            "max_rounds": 10000,
            "early_stopping_rounds": 50,
            "max_rows_limit": null,
            "max_cols_limit": null
        },
        "preprocessing": {
            "columns_preprocessing": {
                "E_G_total_assets_on_assets_ratio": [
                    "remove_column"
                ],
                "E_G_total_revenues_on_rev_ratio": [
                    "remove_column"
                ],
                "E_G_total_capital_on_tot_cap_ratio": [
                    "remove_column"
                ]
            },
            "target_preprocessing": [
                "na_exclude"
            ],
            "ml_task": "binary_classification",
            "add_random_feature": true
        },
        "validation_strategy": {
            "validation_type": "kfold",
            "k_folds": 5,
            "shuffle": true,
            "stratify": true,
            "X_path": "AutoML_2016-2024_CashFromOps/X.data",
            "y_path": "AutoML_2016-2024_CashFromOps/y.data",
            "results_path": "AutoML_2016-2024_CashFromOps",
            "cv_path": "AutoML_2016-2024_CashFromOps/cv.data"
        },
        "learner": {
            "model_type": "Xgboost",
            "ml_task": "binary_classification",
            "n_jobs": -1,
            "seed": 1236,
            "objective": "binary:logistic",
            "eta": 0.1,
            "max_depth": 8,
            "min_child_weight": 1,
            "subsample": 1.0,
            "colsample_bytree": 1.0,
            "eval_metric": "auc",
            "explain_level": 1
        },
        "automl_random_state": 1234,
        "ml_task": "binary_classification",
        "explain_level": 1,
        "name": "3_Xgboost_RandomFeature",
        "status": "initialized",
        "final_loss": null,
        "train_time": null,
        "data_type": "original",
        "max_time_for_learner": 72.0
    },
    "saved": [
        "3_Xgboost_RandomFeature/learner_fold_0.xgboost.json",
        "3_Xgboost_RandomFeature/learner_fold_1.xgboost.json",
        "3_Xgboost_RandomFeature/learner_fold_2.xgboost.json",
        "3_Xgboost_RandomFeature/learner_fold_3.xgboost.json",
        "3_Xgboost_RandomFeature/learner_fold_4.xgboost.json"
    ],
    "predictions_fname": "3_Xgboost_RandomFeature/predictions_out_of_folds.csv",
    "metric_name": "auc",
    "final_loss": "-0.858779270025773",
    "train_time": 101.66680407524109,
    "is_stacked": false,
    "joblib_version": "1.4.2",
    "threshold": 0.49095866084098816,
    "single_prediction_time": 0.09521317481994629
}